{
  "episode_id": "train_v30_s42_nnone_e329",
  "image_ids": [
    7511,
    449406,
    384136,
    352582,
    236730
  ],
  "vocab": {
    "cat_ids": [
      611,
      592,
      1202,
      595,
      404,
      885,
      694,
      534,
      474,
      2,
      3,
      4,
      11,
      12,
      15,
      19,
      23,
      27,
      29,
      32,
      34,
      35,
      36,
      41,
      43,
      45,
      48,
      50,
      53,
      56
    ],
    "prompts": {
      "611": [
        "kite"
      ],
      "592": [
        "jean"
      ],
      "1202": [
        "zebra"
      ],
      "595": [
        "jersey"
      ],
      "404": [
        "duffel bag"
      ],
      "885": [
        "ring"
      ],
      "694": [
        "mirror"
      ],
      "534": [
        "hair dryer"
      ],
      "474": [
        "frisbee"
      ],
      "2": [
        "air conditioner"
      ],
      "3": [
        "airplane"
      ],
      "4": [
        "alarm clock"
      ],
      "11": [
        "antenna"
      ],
      "12": [
        "apple"
      ],
      "15": [
        "apron"
      ],
      "19": [
        "armchair"
      ],
      "23": [
        "trash can"
      ],
      "27": [
        "avocado"
      ],
      "29": [
        "awning"
      ],
      "32": [
        "baby buggy"
      ],
      "34": [
        "backpack"
      ],
      "35": [
        "handbag"
      ],
      "36": [
        "suitcase"
      ],
      "41": [
        "ball"
      ],
      "43": [
        "balloon"
      ],
      "45": [
        "banana"
      ],
      "48": [
        "bandanna"
      ],
      "50": [
        "banner"
      ],
      "53": [
        "barrel"
      ],
      "56": [
        "baseball base"
      ]
    }
  },
  "vocab_size": 30,
  "noise": "none",
  "split": "train",
  "baseline": "",
  "seed": 371,
  "meta": {
    "n_images": 5
  }
}